quaternary/__init__.py
quaternary/quaternary.py
quaternary_plots-0.1.0.dist-info/licenses/LICENSE
quaternary_plots-0.1.0.dist-info/METADATA
quaternary_plots-0.1.0.dist-info/WHEEL
quaternary_plots-0.1.0.dist-info/top_level.txt
quaternary_plots-0.1.0.dist-info/RECORD
