Metadata-Version: 2.4
Name: quaternary-plots
Version: 0.1.0
Summary: A Python library for creating quaternary (tetrahedral) compositional plots
Home-page: https://github.com/olivertlord/quaternary-plots
Author: Oliver T. Lord
Author-email: "Oliver T. Lord" <oliver.lord@bristol.ac.uk>
License: GPL-3.0
Requires-Python: >=3.7
License-File: LICENSE
Requires-Dist: numpy>=1.20.0
Requires-Dist: plotly>=5.0.0
Requires-Dist: scipy>=1.7.0
Provides-Extra: dev
Requires-Dist: pytest>=7.0.0; extra == "dev"
Requires-Dist: pytest-cov>=3.0.0; extra == "dev"
Dynamic: author
Dynamic: home-page
Dynamic: license-file
Dynamic: requires-python
